async_task_pipeline/__init__.py
async_task_pipeline/py.typed
async_task_pipeline/base/__init__.py
async_task_pipeline/base/item.py
async_task_pipeline/base/models.py
async_task_pipeline/base/pipeline.py
async_task_pipeline/base/stage.py
async_task_pipeline/utils/__init__.py
async_task_pipeline/utils/analysis.py
async_task_pipeline/utils/logging.py
async_task_pipeline/utils/metrics.py
async_task_pipeline-0.1.10.dist-info/METADATA
async_task_pipeline-0.1.10.dist-info/WHEEL
async_task_pipeline-0.1.10.dist-info/licenses/LICENSE
async_task_pipeline-0.1.10.dist-info/RECORD
