Metadata-Version: 2.4
Name: async-task-pipeline
Version: 0.1.10
Summary: A framework for processing streaming data through CPU-intensive tasks while maintaining order and tracking latency
Project-URL: Homepage, https://github.com/mouchenghao/async-task-pipeline
Project-URL: Repository, https://github.com/mouchenghao/async-task-pipeline
Project-URL: Issues, https://github.com/mouchenghao/async-task-pipeline/issues
Author-email: Chenghao Mou <mouchenghao@gmail.com>
License-File: LICENSE
Keywords: async,data-processing,pipeline,streaming
Classifier: Development Status :: 3 - Alpha
Classifier: Intended Audience :: Developers
Classifier: License :: OSI Approved :: MIT License
Classifier: Programming Language :: Python :: 3
Classifier: Programming Language :: Python :: 3.12
Classifier: Programming Language :: Python :: 3.13
Classifier: Topic :: Software Development :: Libraries :: Python Modules
Classifier: Topic :: System :: Distributed Computing
Requires-Python: <3.12,>=3.11
Requires-Dist: pydantic>=2.11.5
Requires-Dist: returns>=0.25.0
Requires-Dist: rich>=14.0.0
Provides-Extra: dev
Requires-Dist: bump-my-version>=0.26.0; extra == 'dev'
Requires-Dist: pre-commit>=4.0.0; extra == 'dev'
Requires-Dist: pytest-asyncio>=0.24.0; extra == 'dev'
Requires-Dist: pytest-cov>=5.0.0; extra == 'dev'
Requires-Dist: pytest-watch>=4.2.0; extra == 'dev'
Requires-Dist: pytest>=8.0.0; extra == 'dev'
Requires-Dist: ruff>=0.7.0; extra == 'dev'
Requires-Dist: tox>=4.0.0; extra == 'dev'
